zeus_cod_bo6_bot_manager/__init__.py
zeus_cod_bo6_bot_manager/__main__.py
zeus_cod_bo6_bot_manager/backend/__init__.py
zeus_cod_bo6_bot_manager/backend/app.py
zeus_cod_bo6_bot_manager/backend/database.py
zeus_cod_bo6_bot_manager/backend/endpoints.py
zeus_cod_bo6_bot_manager/backend/handlers/__init__.py
zeus_cod_bo6_bot_manager/backend/handlers/misc_handlers.py
zeus_cod_bo6_bot_manager/backend/handlers/servers_handler.py
zeus_cod_bo6_bot_manager/backend/utils/__init__.py
zeus_cod_bo6_bot_manager/backend/utils/misc_utils.py
zeus_cod_bo6_bot_manager/backend/utils/response_helper.py
zeus_cod_bo6_bot_manager/backend/utils/server_utils.py
zeus_cod_bo6_bot_manager/frontend_ui/index.html
zeus_cod_bo6_bot_manager/frontend_ui/jsconfig.json
zeus_cod_bo6_bot_manager/frontend_ui/package.json
zeus_cod_bo6_bot_manager/frontend_ui/vite.config.mjs
zeus_cod_bo6_bot_manager/frontend_ui/public/favicon.ico
zeus_cod_bo6_bot_manager/frontend_ui/src/App.vue
zeus_cod_bo6_bot_manager/frontend_ui/src/main.js
zeus_cod_bo6_bot_manager/frontend_ui/src/api/axiosInstance.js
zeus_cod_bo6_bot_manager/frontend_ui/src/api/repositories/botManagerRepository.js
zeus_cod_bo6_bot_manager/frontend_ui/src/api/repositories/index.js
zeus_cod_bo6_bot_manager/frontend_ui/src/assets/fonts/CutiveMono-Regular.ttf
zeus_cod_bo6_bot_manager/frontend_ui/src/assets/fonts/Poppins-Bold.ttf
zeus_cod_bo6_bot_manager/frontend_ui/src/assets/fonts/Poppins-Regular.ttf
zeus_cod_bo6_bot_manager/frontend_ui/src/assets/fonts/Poppins-SemiBold.ttf
zeus_cod_bo6_bot_manager/frontend_ui/src/assets/icons/bo6.png
zeus_cod_bo6_bot_manager/frontend_ui/src/assets/icons/database-storage.svg
zeus_cod_bo6_bot_manager/frontend_ui/src/assets/icons/github.png
zeus_cod_bo6_bot_manager/frontend_ui/src/assets/icons/github.svg
zeus_cod_bo6_bot_manager/frontend_ui/src/assets/icons/server_empty.svg
zeus_cod_bo6_bot_manager/frontend_ui/src/assets/styles/global.css
zeus_cod_bo6_bot_manager/frontend_ui/src/components/CommonEmptyStateCard.vue
zeus_cod_bo6_bot_manager-1.0.1.dist-info/LICENSE
zeus_cod_bo6_bot_manager-1.0.1.dist-info/METADATA
zeus_cod_bo6_bot_manager-1.0.1.dist-info/WHEEL
zeus_cod_bo6_bot_manager-1.0.1.dist-info/entry_points.txt
zeus_cod_bo6_bot_manager-1.0.1.dist-info/top_level.txt
zeus_cod_bo6_bot_manager-1.0.1.dist-info/RECORD
