Metadata-Version: 2.1
Name: zeus_cod_bo6_bot_manager
Version: 1.0.1
Summary: A admin panel for controlling gamepad inputs and managing HWIDs.
Home-page: https://github.com/satyajiit/CodBo6_Bot_Manager_Zeus
Author: GamesPatch
Author-email: hello.theappstack@gmail.com
License: MIT
Classifier: Programming Language :: Python :: 3
Classifier: License :: OSI Approved :: MIT License
Classifier: Operating System :: Microsoft :: Windows
Classifier: Operating System :: POSIX :: Linux
Requires-Python: >=3.6
License-File: LICENSE
Requires-Dist: flask-cors
Requires-Dist: Flask
Requires-Dist: PySide6
Requires-Dist: PyQtWebEngine
Requires-Dist: pyperclip
